README.rst
setup.cfg
setup.py
visualops/__init__.py
visualops/main.py
visualops.egg-info/PKG-INFO
visualops.egg-info/SOURCES.txt
visualops.egg-info/dependency_links.txt
visualops.egg-info/entry_points.txt
visualops.egg-info/not-zip-safe
visualops.egg-info/pbr.json
visualops.egg-info/requires.txt
visualops.egg-info/top_level.txt
visualops/cmd/__init__.py
visualops/cmd/session.py
visualops/cmd/app/__init__.py
visualops/cmd/app/clone.py
visualops/cmd/app/info.py
visualops/cmd/app/list.py
visualops/cmd/app/restart.py
visualops/cmd/app/start.py
visualops/cmd/app/stop.py
visualops/cmd/app/terminate.py
visualops/cmd/db/__init__.py
visualops/cmd/db/reset.py
visualops/cmd/project/__init__.py
visualops/cmd/project/list.py
visualops/cmd/project/select.py
visualops/cmd/stack/__init__.py
visualops/cmd/stack/delete.py
visualops/cmd/stack/info.py
visualops/cmd/stack/list.py
visualops/cmd/stack/pull.py
visualops/cmd/stack/push.py
visualops/cmd/stack/run.py
visualops/utils/Result.py
visualops/utils/__init__.py
visualops/utils/boot2docker.py
visualops/utils/bootstrap.py
visualops/utils/constant.py
visualops/utils/db.py
visualops/utils/dockervisops.py
visualops/utils/rpc.py
visualops/utils/utils.py