Metadata-Version: 1.0
Name: visualops
Version: 0.3.2
Summary: VisualOps CLI
Home-page: https://github.com/MadeiraCloud/cli
Author: Thibault Bronchain
Author-email: thibault@visualops.io
License: LICENSE.txt
Platform: UNKNOWN
